./.gitignore
./LICENSE
./PKG-INFO
./README.md
./__init__.py
./models.py
./pyproject.toml
./server.py
task_management_mcp-1.0.2.dist-info/METADATA
task_management_mcp-1.0.2.dist-info/WHEEL
task_management_mcp-1.0.2.dist-info/entry_points.txt
task_management_mcp-1.0.2.dist-info/licenses/LICENSE
task_management_mcp-1.0.2.dist-info/RECORD
