Metadata-Version: 2.4
Name: task-management-mcp
Version: 1.0.2
Summary: MCP Server for Task Management API
Project-URL: Homepage, https://github.com/Aayush9029/mcp-server
Project-URL: Documentation, https://github.com/Aayush9029/mcp-server#readme
Project-URL: Repository, https://github.com/Aayush9029/mcp-server
Project-URL: Issues, https://github.com/Aayush9029/mcp-server/issues
Author-email: Aayush Pokharel <developer@lovedoingthings.com>
License: MIT
License-File: LICENSE
Keywords: api,llm,mcp,task-management
Classifier: Development Status :: 4 - Beta
Classifier: Intended Audience :: Developers
Classifier: License :: OSI Approved :: MIT License
Classifier: Programming Language :: Python :: 3
Classifier: Programming Language :: Python :: 3.11
Classifier: Programming Language :: Python :: 3.12
Classifier: Topic :: Software Development :: Libraries :: Python Modules
Requires-Python: >=3.11
Requires-Dist: httpx>=0.27.0
Requires-Dist: mcp>=1.0.0
Requires-Dist: pydantic>=2.9.0
Provides-Extra: dev
Requires-Dist: build>=1.2.0; extra == 'dev'
Requires-Dist: pytest-asyncio>=0.24.0; extra == 'dev'
Requires-Dist: pytest-httpx>=0.32.0; extra == 'dev'
Requires-Dist: pytest>=8.3.0; extra == 'dev'
Requires-Dist: twine>=5.1.0; extra == 'dev'
